gemini_image_generator/__init__.py
gemini_image_generator/cli.py
gemini_image_generator/generator.py
gemini_image_generator-1.0.0.dist-info/licenses/LICENSE
gemini_image_generator-1.0.0.dist-info/METADATA
gemini_image_generator-1.0.0.dist-info/WHEEL
gemini_image_generator-1.0.0.dist-info/entry_points.txt
gemini_image_generator-1.0.0.dist-info/top_level.txt
gemini_image_generator-1.0.0.dist-info/RECORD
