Metadata-Version: 2.4
Name: gemini-image-generator
Version: 1.0.0
Summary: A robust Python library and CLI to batch-generate images using the Google Gemini API, featuring resumable sessions and smart file management.
Author-email: zhanngpenng <zhanngpenng@gmail.com>
License: MIT License
Keywords: gemini,ai,image generation,batch processing,cli
Classifier: Development Status :: 5 - Production/Stable
Classifier: Intended Audience :: Developers
Classifier: License :: OSI Approved :: MIT License
Classifier: Programming Language :: Python :: 3
Classifier: Programming Language :: Python :: 3.9
Classifier: Programming Language :: Python :: 3.10
Classifier: Programming Language :: Python :: 3.11
Classifier: Topic :: Scientific/Engineering :: Image Processing
Classifier: Topic :: Utilities
Requires-Python: >=3.9
License-File: LICENSE
Requires-Dist: google-generativeai
Requires-Dist: Pillow
Requires-Dist: PyYAML
Requires-Dist: python-dotenv
Requires-Dist: jieba
Dynamic: license-file
